mark_client/__init__.py
mark_client/conftest.py
mark_client/mark_python_client.py
mark_python_client-1.0.0.dist-info/LICENSE
mark_python_client-1.0.0.dist-info/METADATA
mark_python_client-1.0.0.dist-info/WHEEL
mark_python_client-1.0.0.dist-info/top_level.txt
mark_python_client-1.0.0.dist-info/RECORD
