Metadata-Version: 2.1
Name: mark-python-client
Version: 1.0.0
Summary: A script to connect to the MARK server via python
Home-page: https://gitlab.cylab.be/cylab/mark-python-client
Author: Georgi Nikolov
Author-email: contact@cylab.be
License: UNKNOWN
Platform: UNKNOWN
Classifier: Programming Language :: Python :: 2.7
Classifier: License :: OSI Approved :: MIT License
Classifier: Operating System :: OS Independent
